pyflare/__init__.py
pyflare/jars/commons-0.0.44.jar
pyflare/jars/heimdall-0.0.44.jar
pyflare/jars/spark-authz-0.0.44.jar
pyflare/sdk/__init__.py
pyflare/sdk/config/__init__.py
pyflare/sdk/config/constants.py
pyflare/sdk/config/read_config.py
pyflare/sdk/config/write_config.py
pyflare/sdk/core/__init__.py
pyflare/sdk/core/dataos_input.py
pyflare/sdk/core/dataos_output.py
pyflare/sdk/core/decorator.py
pyflare/sdk/core/minerva_input.py
pyflare/sdk/core/session_builder.py
pyflare/sdk/depots/__init__.py
pyflare/sdk/depots/client.py
pyflare/sdk/readers/__init__.py
pyflare/sdk/readers/bigquery_reader.py
pyflare/sdk/readers/delta_reader.py
pyflare/sdk/readers/elasticsearch_reader.py
pyflare/sdk/readers/fastbase_reader.py
pyflare/sdk/readers/file_reader.py
pyflare/sdk/readers/iceberg_reader.py
pyflare/sdk/readers/jdbc_reader.py
pyflare/sdk/readers/minerva_reader.py
pyflare/sdk/readers/reader.py
pyflare/sdk/readers/snowflake_reader.py
pyflare/sdk/utils/__init__.py
pyflare/sdk/utils/generic_utils.py
pyflare/sdk/utils/pyflare_exceptions.py
pyflare/sdk/utils/pyflare_logger.py
pyflare/sdk/writers/__init__.py
pyflare/sdk/writers/bigquery_writer.py
pyflare/sdk/writers/delta_writer.py
pyflare/sdk/writers/elasticsearch_writer.py
pyflare/sdk/writers/fastbase_writer.py
pyflare/sdk/writers/file_writer.py
pyflare/sdk/writers/iceberg_writer.py
pyflare/sdk/writers/jdbc_writer.py
pyflare/sdk/writers/snowflake_writer.py
pyflare/sdk/writers/writer.py
pyflare/secrets/__init__.py
pyflare/secrets/abfss.py
pyflare/secrets/gcs.py
pyflare/secrets/s3.py
dataos_pyflare-0.1.13.dist-info/LICENSE
dataos_pyflare-0.1.13.dist-info/METADATA
dataos_pyflare-0.1.13.dist-info/WHEEL
dataos_pyflare-0.1.13.dist-info/top_level.txt
dataos_pyflare-0.1.13.dist-info/RECORD
