Metadata-Version: 2.1
Name: dataos-pyflare
Version: 0.1.13
Summary: Pyspark bridge to dataos
Home-page: https://bitbucket.org/rubik_/dataos-pyspark-sdk
Author: Modern labs
Author-email: Mayank Sharma <mayank.sharma@tmdc.io>
License: Copyright (c) 2018 The Python Packaging Authority
Project-URL: Homepage, https://bitbucket.org/rubik_/dataos-pyspark-sdk
Keywords: dataos,python flare,pyflare,dataos-pyflare
Classifier: Development Status :: 3 - Alpha
Classifier: Intended Audience :: Developers
Classifier: Intended Audience :: Customer Service
Classifier: Intended Audience :: Information Technology
Classifier: Intended Audience :: Science/Research
Classifier: Operating System :: OS Independent
Classifier: License :: OSI Approved :: MIT License
Classifier: Programming Language :: Python :: 3
Requires-Python: >=3.7, <4
License-File: LICENSE
